tryon/__init__.py
tryon/agents/__init__.py
tryon/agents/model_swap/__init__.py
tryon/agents/model_swap/agent.py
tryon/agents/model_swap/tools.py
tryon/agents/vton/__init__.py
tryon/agents/vton/agent.py
tryon/agents/vton/tools.py
tryon/api/__init__.py
tryon/api/flux2.py
tryon/api/kling_ai.py
tryon/api/nova_canvas.py
tryon/api/segmind.py
tryon/api/veo.py
tryon/api/lumaAI/__init__.py
tryon/api/lumaAI/adapter.py
tryon/api/lumaAI/luma_video_adapter.py
tryon/api/nano_banana/__init__.py
tryon/api/nano_banana/adapter.py
tryon/api/openAI/__init__.py
tryon/api/openAI/image_adapter.py
tryon/api/openAI/video_adapter.py
tryon/datasets/__init__.py
tryon/datasets/base.py
tryon/datasets/example_usage.py
tryon/datasets/fashion_mnist.py
tryon/datasets/subjects200k.py
tryon/datasets/viton_hd.py
tryon/models/__init__.py
tryon/preprocessing/__init__.py
tryon/preprocessing/extract_garment_new.py
tryon/preprocessing/preprocess_garment.py
tryon/preprocessing/preprocess_human.py
tryon/preprocessing/utils.py
tryon/preprocessing/captioning/__init__.py
tryon/preprocessing/captioning/generate_caption.py
tryon/preprocessing/sam2/__init__.py
tryon/preprocessing/u2net/__init__.py
tryon/preprocessing/u2net/data_loader.py
tryon/preprocessing/u2net/load_u2net.py
tryon/preprocessing/u2net/u2net_cloth_segm.py
tryon/preprocessing/u2net/u2net_human_segm.py
tryon/preprocessing/u2net/utils.py
tryondiffusion/__init__.py
tryondiffusion/diffusion.py
tryondiffusion/ema.py
tryondiffusion/network.py
tryondiffusion/trainer.py
tryondiffusion/pre_processing/__init__.py
tryondiffusion/pre_processing/generate_cloth_agnostic_rgb.py
tryondiffusion/pre_processing/generate_segmented_garment.py
tryondiffusion/pre_processing/save_pose_embeddings.py
tryondiffusion/pre_processing/segment_cloth_u2net.py
tryondiffusion/pre_processing/openpose_pytorch/__init__.py
tryondiffusion/pre_processing/openpose_pytorch/body_pose.py
tryondiffusion/pre_processing/openpose_pytorch/model.py
opentryon-0.0.2.dist-info/METADATA
opentryon-0.0.2.dist-info/WHEEL
opentryon-0.0.2.dist-info/top_level.txt
opentryon-0.0.2.dist-info/RECORD
