Metadata-Version: 2.4
Name: opentryon
Version: 0.0.2
Summary: Open-source AI toolkit for fashion tech and virtual try-on
Home-page: https://github.com/tryonlabs/opentryon
Author: TryOn Labs
Author-email: contact@tryonlabs.ai
License: CC-BY-NC-4.0
Project-URL: Documentation, https://tryonlabs.github.io/opentryon/
Project-URL: Source, https://github.com/tryonlabs/opentryon
Project-URL: Bug Reports, https://github.com/tryonlabs/opentryon/issues
Project-URL: Discord, https://discord.gg/T5mPpZHxkY
Keywords: virtual try-on,fashion tech,diffusion models,garment segmentation,pose estimation,outfit generation,try-on diffusion,computer vision,deep learning,artificial intelligence,image generation
Classifier: Development Status :: 3 - Alpha
Classifier: Intended Audience :: Developers
Classifier: Intended Audience :: Science/Research
Classifier: License :: Free for non-commercial use
Classifier: Operating System :: OS Independent
Classifier: Programming Language :: Python :: 3
Classifier: Topic :: Scientific/Engineering :: Artificial Intelligence
Classifier: Topic :: Scientific/Engineering :: Image Processing
Classifier: Programming Language :: Python :: 3.10
Classifier: Programming Language :: Python :: 3.11
Classifier: Programming Language :: Python :: 3.12
Classifier: License :: Free For Home Use
Classifier: License :: Other/Proprietary License
Requires-Python: >=3.10
Requires-Dist: torch==2.1.2
Requires-Dist: torchvision==0.16.2
Requires-Dist: numpy==1.26.4
Requires-Dist: opencv-python==4.8.1.78
Requires-Dist: pillow==10.1.0
Requires-Dist: tqdm==4.66.1
Requires-Dist: scikit-image==0.22.0
Requires-Dist: python-dotenv==1.0.1
Requires-Dist: transformers==4.42.4
Requires-Dist: boto3==1.40.64
Requires-Dist: requests>=2.31.0
Requires-Dist: PyJWT>=2.10.1
Requires-Dist: google-genai>=1.52.0
Requires-Dist: fastapi==0.124.0
Requires-Dist: uvicorn[standard]==0.38.0
Requires-Dist: python-multipart==0.0.20
Requires-Dist: lumaai>=1.18.1
Requires-Dist: langchain>=1.0.0
Requires-Dist: langchain-openai>=0.2.0
Requires-Dist: langchain-anthropic>=0.2.0
Requires-Dist: langchain-google-genai>=2.0.0
Requires-Dist: pydantic>=2.0.0
Provides-Extra: demos
Requires-Dist: gradio>=6.0.0; extra == "demos"
Provides-Extra: training
Requires-Dist: diffusers>=0.21.0; extra == "training"
Requires-Dist: accelerate>=0.20.0; extra == "training"
Provides-Extra: all
Requires-Dist: gradio>=6.0.0; extra == "all"
Requires-Dist: diffusers>=0.21.0; extra == "all"
Requires-Dist: accelerate>=0.20.0; extra == "all"
Dynamic: author
Dynamic: author-email
Dynamic: classifier
Dynamic: description
Dynamic: description-content-type
Dynamic: home-page
Dynamic: keywords
Dynamic: license
Dynamic: project-url
Dynamic: provides-extra
Dynamic: requires-dist
Dynamic: requires-python
Dynamic: summary
